{
  "prefix": ".",
  "names": {
    "1": { "name": "Aabartan Man Karmacharya", "userId": "" },
    "2": { "name": "Aagav Ojha", "userId": "" },
    "3": { "name": "Aakrisht Sharma Paudel", "userId": "" },
    "4": { "name": "Aayush Dhungana", "userId": "" },
    "5": { "name": "Aayush Subedi", "userId": "" },
    "6": { "name": "Abhaya Shrestha", "userId": "" },
    "7": { "name": "Abhinav Karn", "userId": "" },
    "8": { "name": "Abhishek Tharu", "userId": "" },
    "9": { "name": "Abhishu Panthi", "userId": "" },
    "10": { "name": "Abisekh Pandey", "userId": "" },
    "11": { "name": "Aditya Kumar Shah", "userId": "" },
    "12": { "name": "Alex Shrestha", "userId": "" },
    "13": { "name": "Aman Ranabhat", "userId": "" },
    "14": { "name": "Anup Kumar Jha", "userId": "" },
    "15": { "name": "Arya Dangol", "userId": "" },
    "16": { "name": "Aryan Dahal", "userId": "" },
    "17": { "name": "Asmit Khanal", "userId": "" },
    "18": { "name": "Avinash Kumar Yadav", "userId": "" },
    "19": { "name": "Bhim Prasad Upadhyaya", "userId": "" },
    "20": { "name": "Bibek Gautam", "userId": "" },
    "21": { "name": "Bibidh Subedi", "userId": "" },
    "22": { "name": "Biprash Pandey", "userId": "" },
    "23": { "name": "Chandan Kumar Shah", "userId": "" },
    "24": { "name": "Darpan Giri", "userId": "" },
    "25": { "name": "Dinesh Bhatta", "userId": "" },
    "26": { "name": "Dipesh S. Saud", "userId": "" },
    "27": { "name": "Diwas Pantha", "userId": "" },
    "28": { "name": "Diwas Shrestha", "userId": "" },
    "29": { "name": "Dumajal Malla", "userId": "" },
    "30": { "name": "Gagan Kumar Dahal", "userId": "" },
    "31": { "name": "Gaurab Khatry", "userId": "" },
    "32": { "name": "Homraj KC", "userId": "" },
    "33": { "name": "Hridan Bhattarai", "userId": "" },
    "34": { "name": "Ishan Gautam", "userId": "" },
    "35": { "name": "Janak Singh Pujara", "userId": "" },
    "36": { "name": "Jenif Khadka", "userId": "" },
    "37": { "name": "Kajal Kumari Chaudhary", "userId": "" },
    "38": { "name": "Kapil Pokhrel", "userId": "" },
    "39": { "name": "Krish Bansal", "userId": "" },
    "40": { "name": "Kushal Gautam", "userId": "" },
    "41": { "name": "Kushal KC", "userId": "" },
    "42": { "name": "Kushal Regmi", "userId": "" },
    "43": { "name": "Lav Raj Karn", "userId": "" },
    "44": { "name": "Laxmi Kumari", "userId": "" },
    "45": { "name": "Mahesh Bhandari", "userId": "" },
    "46": { "name": "Mission Baraily", "userId": "" },
    "47": { "name": "Nabina Thapa", "userId": "" },
    "48": { "name": "Nayan Khussu", "userId": "" }
  }
}
